{"cameraMode":{"drawMode":0,"name":"Shaded","section":"Shading Mode"},"sceneLighting":true,"audioPlay":false,"sceneViewState":{"showFog":true,"showMaterialUpdate":false,"showSkybox":true,"showFlares":true,"showImageEffects":true,"showParticleSystems":true},"in2DMode":false,"pivot":{"x":-0.592620849609375,"y":7.221864700317383,"z":-1.5173792839050294},"rotation":{"x":-0.2987183928489685,"y":-0.6974210143089294,"z":-0.4146476984024048,"w":0.5024327039718628},"size":30.196603775024415,"orthographic":false}